uswapper/__init__.py
uswapper-2.2.dist-info/METADATA
uswapper-2.2.dist-info/WHEEL
uswapper-2.2.dist-info/top_level.txt
uswapper-2.2.dist-info/RECORD
